rapidstream/__init__.py
rapidstream/assets/__init__.py
rapidstream/assets/cluster/__init__.py
rapidstream/assets/cluster/client.py
rapidstream/assets/cluster/task.py
rapidstream/assets/cluster/tasks/__init__.py
rapidstream/assets/cluster/tasks/simulation.py
rapidstream/assets/cluster/tasks/vitis_hls.py
rapidstream/assets/cluster/tasks/vivado.py
rapidstream/assets/cluster/util.py
rapidstream/assets/dataflow/__init__.py
rapidstream/assets/dataflow/ip/lutram.v
rapidstream/assets/dataflow/ip/stream_fmacc_synth.v
rapidstream/assets/dataflow/sources.py
rapidstream/assets/device/__init__.py
rapidstream/assets/device/common.py
rapidstream/assets/device/device_factory.py
rapidstream/assets/device/schedule.py
rapidstream/assets/device/virtual_device.py
rapidstream/assets/device_library/__init__.py
rapidstream/assets/device_library/library.py
rapidstream/assets/device_library/u250/__init__.py
rapidstream/assets/device_library/u250/u250.py
rapidstream/assets/device_library/u280/__init__.py
rapidstream/assets/device_library/u280/u280.py
rapidstream/assets/device_library/u50/__init__.py
rapidstream/assets/device_library/u50/partition_schedule.json
rapidstream/assets/device_library/u50/u50.py
rapidstream/assets/device_library/vck190/__init__.py
rapidstream/assets/device_library/vck190/noc_position.py
rapidstream/assets/device_library/vck190/partition_schedule.json
rapidstream/assets/device_library/vck190/vck190.py
rapidstream/assets/tcls/get_netlist_info.tcl
rapidstream/assets/tcls/package_xo.tcl
rapidstream/assets/tcls/run_cosim.tcl
rapidstream/assets/templates/__init__.py
rapidstream/assets/templates/exporter/grouped-module.v
rapidstream/assets/templates/exporter/includes/common-header.v
rapidstream/assets/templates/exporter/includes/header-parameters.v
rapidstream/assets/templates/exporter/includes/header-ports.v
rapidstream/assets/templates/exporter/includes/module-footer.v
rapidstream/assets/templates/exporter/includes/module-header.v
rapidstream-2024.1.dist-info/METADATA
rapidstream-2024.1.dist-info/WHEEL
rapidstream-2024.1.dist-info/entry_points.txt
rapidstream-2024.1.dist-info/RECORD
