Metadata-Version: 2.1
Name: rapidstream
Version: 2024.1
Summary: RapidStream: Agile and efficient development flow for modern FPGAs
Author: RapidStream Design Automation, Inc.
Author-email: info@rapidstream-da.com
Requires-Python: >=3.10,<4.0
Classifier: Programming Language :: Python :: 3
Classifier: Programming Language :: Python :: 3.10
Classifier: Programming Language :: Python :: 3.11
Classifier: Programming Language :: Python :: 3.12
Requires-Dist: bokeh (>=3.3.4)
Requires-Dist: click (>=8.1.7,<9.0.0)
Requires-Dist: cryptography (>=42.0.2,<43.0.0)
Requires-Dist: dask[distributed] (>=2024.2.0,<2025.0.0)
Requires-Dist: ed25519 (>=1.5,<2.0)
Requires-Dist: igraph (>=0.11.3,<0.12.0)
Requires-Dist: jinja2 (>=3.1.3,<4.0.0)
Requires-Dist: pandas (>=2.2.0,<3.0.0)
Requires-Dist: prettytable (>=3.9.0,<4.0.0)
Requires-Dist: psutil (>=5.9.8,<6.0.0)
Requires-Dist: pulp (>=2.8.0,<3.0.0)
Requires-Dist: py-machineid (>=0.5.1,<0.6.0)
Requires-Dist: pydantic (>=2.6.1,<3.0.0)
Requires-Dist: pyslang (>=5.0.0,<6.0.0)
Requires-Dist: rapidwright (>=2023.2.1,<2024.0.0)
Requires-Dist: requests (>=2.31.0,<3.0.0)
Requires-Dist: treelib (>=1.7.0,<2.0.0)
